{"packages":{"nirzol\/efg-logger":{"dev-master":{"name":"nirzol\/efg-logger","description":"Base module for custom loggers. This module implements Doctrine log writer with Zend log component.","keywords":[],"homepage":"","version":"dev-master","version_normalized":"9999999-dev","license":[],"authors":[{"name":"Nirzol","email":"grondin.eric@gmail.com"}],"source":{"type":"git","url":"https:\/\/github.com\/Nirzol\/EfgLogger.git","reference":"b6a9c83fac95cbedd48e043d9fa431ec2f1cf1d5"},"dist":{"type":"zip","url":"https:\/\/api.github.com\/repos\/Nirzol\/EfgLogger\/zipball\/b6a9c83fac95cbedd48e043d9fa431ec2f1cf1d5","reference":"b6a9c83fac95cbedd48e043d9fa431ec2f1cf1d5","shasum":""},"type":"library","time":"2016-03-24T10:29:53+00:00","autoload":{"psr-0":{"EfgLogger\\":"src\/"}},"require":{"php":">=5.4","zendframework\/zendframework":">=2.3"},"uid":729979}}}}