{"packages":{"contao-components\/simplemodal":{"1.2.0":{"name":"contao-components\/simplemodal","description":"SimpleModal integration for Contao Open Source CMS","keywords":[],"homepage":"","version":"1.2.0","version_normalized":"1.2.0.0","license":["MIT"],"authors":[{"name":"Leo Feyer","homepage":"https:\/\/github.com\/leofeyer"}],"source":{"type":"git","url":"https:\/\/github.com\/contao-components\/simplemodal.git","reference":"770e419c7790d6e0b3a56392d075becda51261f0"},"dist":{"type":"zip","url":"https:\/\/api.github.com\/repos\/contao-components\/simplemodal\/zipball\/770e419c7790d6e0b3a56392d075becda51261f0","reference":"770e419c7790d6e0b3a56392d075becda51261f0","shasum":""},"type":"component","time":"2014-08-22T08:44:33+00:00","extra":{"component":{"scripts":["js\/simplemodal.min.js"],"styles":["css\/simplemodal.min.css"],"files":["images\/*"]}},"require":{"robloach\/component-installer":"~0.0"},"uid":221654},"1.2.0.1":{"name":"contao-components\/simplemodal","description":"SimpleModal integration for Contao Open Source CMS","keywords":[],"homepage":"","version":"1.2.0.1","version_normalized":"1.2.0.1","license":["MIT"],"authors":[{"name":"Leo Feyer","homepage":"https:\/\/github.com\/leofeyer"}],"source":{"type":"git","url":"https:\/\/github.com\/contao-components\/simplemodal.git","reference":"c64870657b47b9457ce45bf5482e63408919de57"},"dist":{"type":"zip","url":"https:\/\/api.github.com\/repos\/contao-components\/simplemodal\/zipball\/c64870657b47b9457ce45bf5482e63408919de57","reference":"c64870657b47b9457ce45bf5482e63408919de57","shasum":""},"type":"contao-component","time":"2014-11-06T09:03:58+00:00","require":{"contao-components\/installer":"~1.0"},"uid":264464},"1.2.1":{"name":"contao-components\/simplemodal","description":"SimpleModal integration for Contao Open Source CMS","keywords":[],"homepage":"","version":"1.2.1","version_normalized":"1.2.1.0","license":["MIT"],"authors":[{"name":"Leo Feyer","homepage":"https:\/\/github.com\/leofeyer"}],"source":{"type":"git","url":"https:\/\/github.com\/contao-components\/simplemodal.git","reference":"a285174dcbe67406ff88cee1da63b8aa4ee55281"},"dist":{"type":"zip","url":"https:\/\/api.github.com\/repos\/contao-components\/simplemodal\/zipball\/a285174dcbe67406ff88cee1da63b8aa4ee55281","reference":"a285174dcbe67406ff88cee1da63b8aa4ee55281","shasum":""},"type":"contao-component","time":"2016-03-22T14:42:28+00:00","require":{"contao-components\/installer":"~1.0"},"uid":747161},"1.2.2":{"name":"contao-components\/simplemodal","description":"SimpleModal integration for Contao Open Source CMS","keywords":[],"homepage":"","version":"1.2.2","version_normalized":"1.2.2.0","license":["MIT"],"authors":[{"name":"Leo Feyer","homepage":"https:\/\/github.com\/leofeyer"}],"source":{"type":"git","url":"https:\/\/github.com\/contao-components\/simplemodal.git","reference":"8537da8f5bf67461cbdf65b187076e467e8f046c"},"dist":{"type":"zip","url":"https:\/\/api.github.com\/repos\/contao-components\/simplemodal\/zipball\/8537da8f5bf67461cbdf65b187076e467e8f046c","reference":"8537da8f5bf67461cbdf65b187076e467e8f046c","shasum":""},"type":"contao-component","time":"2016-04-21T09:32:17+00:00","require":{"contao-components\/installer":"~1.0"},"uid":787432},"1.2.3":{"name":"contao-components\/simplemodal","description":"SimpleModal integration for Contao Open Source CMS","keywords":[],"homepage":"","version":"1.2.3","version_normalized":"1.2.3.0","license":["MIT"],"authors":[{"name":"Leo Feyer","homepage":"https:\/\/github.com\/leofeyer"}],"source":{"type":"git","url":"https:\/\/github.com\/contao-components\/simplemodal.git","reference":"41a88e2087d49a76c67e5337859909865945b078"},"dist":{"type":"zip","url":"https:\/\/api.github.com\/repos\/contao-components\/simplemodal\/zipball\/41a88e2087d49a76c67e5337859909865945b078","reference":"41a88e2087d49a76c67e5337859909865945b078","shasum":""},"type":"contao-component","time":"2016-05-18T07:06:01+00:00","require":{"contao-components\/installer":"~1.0"},"uid":825518},"dev-develop":{"name":"contao-components\/simplemodal","description":"SimpleModal integration for Contao Open Source CMS","keywords":[],"homepage":"","version":"dev-develop","version_normalized":"dev-develop","license":["MIT"],"authors":[{"name":"Leo Feyer","homepage":"https:\/\/github.com\/leofeyer"}],"source":{"type":"git","url":"https:\/\/github.com\/contao-components\/simplemodal.git","reference":"d96af4d7c765ee7fd4d8c2ed43d4df3cdfb33e61"},"dist":{"type":"zip","url":"https:\/\/api.github.com\/repos\/contao-components\/simplemodal\/zipball\/d96af4d7c765ee7fd4d8c2ed43d4df3cdfb33e61","reference":"d96af4d7c765ee7fd4d8c2ed43d4df3cdfb33e61","shasum":""},"type":"contao-component","time":"2016-04-25T11:49:32+00:00","require":{"contao-components\/installer":"~1.0"},"uid":792959},"dev-master":{"name":"contao-components\/simplemodal","description":"SimpleModal integration for Contao Open Source CMS","keywords":[],"homepage":"","version":"dev-master","version_normalized":"9999999-dev","license":["MIT"],"authors":[{"name":"Leo Feyer","homepage":"https:\/\/github.com\/leofeyer"}],"source":{"type":"git","url":"https:\/\/github.com\/contao-components\/simplemodal.git","reference":"41a88e2087d49a76c67e5337859909865945b078"},"dist":{"type":"zip","url":"https:\/\/api.github.com\/repos\/contao-components\/simplemodal\/zipball\/41a88e2087d49a76c67e5337859909865945b078","reference":"41a88e2087d49a76c67e5337859909865945b078","shasum":""},"type":"contao-component","time":"2016-05-18T07:06:01+00:00","require":{"contao-components\/installer":"~1.0"},"uid":221655}}}}